auto_karaoke/__init__.py
auto_karaoke/main.py
auto_karaoke/sampleKaraokeMugen.ass
auto_karaoke-0.0.6.dist-info/LICENSE
auto_karaoke-0.0.6.dist-info/METADATA
auto_karaoke-0.0.6.dist-info/WHEEL
auto_karaoke-0.0.6.dist-info/entry_points.txt
auto_karaoke-0.0.6.dist-info/top_level.txt
auto_karaoke-0.0.6.dist-info/RECORD
