Metadata-Version: 2.1
Name: auto-karaoke
Version: 0.0.6
Summary: Approximate word-based subtitle timing for karaokes
Author: DiZeroX
License: MIT License
Project-URL: Homepage, https://github.com/DiZeroX/auto-karaoke
Project-URL: Bug Tracker, https://github.com/DiZeroX/auto-karaoke/issues
Classifier: Programming Language :: Python :: 3
Requires-Python: >=3.9
License-File: LICENSE
Requires-Dist: ass ==0.5.2
Requires-Dist: ffmpeg-python ==0.2.0
Requires-Dist: torch
Requires-Dist: torchaudio
Requires-Dist: torchvision
